bald_spider/__init__.py
bald_spider/crawler.py
bald_spider/event.py
bald_spider/exceptions.py
bald_spider/stats_collector.py
bald_spider/subscriber.py
bald_spider/task_manager.py
bald_spider/core/__init__.py
bald_spider/core/engine.py
bald_spider/core/processor.py
bald_spider/core/scheduler.py
bald_spider/core/downloader/__init__.py
bald_spider/core/downloader/aiohttp_downloader.py
bald_spider/core/downloader/httpx_downloader.py
bald_spider/duplicate_filter/__init__.py
bald_spider/duplicate_filter/aioredis_filter.py
bald_spider/duplicate_filter/memory_filter.py
bald_spider/duplicate_filter/no_filter.py
bald_spider/duplicate_filter/redis_filter.py
bald_spider/http/__init__.py
bald_spider/http/request.py
bald_spider/http/response.py
bald_spider/items/__init__.py
bald_spider/items/items.py
bald_spider/middleware/__init__.py
bald_spider/middleware/default_header.py
bald_spider/middleware/download_delay.py
bald_spider/middleware/middleware_manager.py
bald_spider/middleware/request_ignore.py
bald_spider/middleware/response_code.py
bald_spider/middleware/retry.py
bald_spider/pipeline/__init__.py
bald_spider/pipeline/pipeline_manager.py
bald_spider/settings/__init__.py
bald_spider/settings/default_settings.py
bald_spider/settings/settings_manager.py
bald_spider/spider/__init__.py
bald_spider/utils/__init__.py
bald_spider/utils/date.py
bald_spider/utils/log.py
bald_spider/utils/pqueue.py
bald_spider/utils/project.py
bald_spider/utils/request.py
bald_spider/utils/spider.py
bald_spider/utils/system.py
test/__init__.py
test/baidu_spider/__init__.py
test/baidu_spider/items.py
test/baidu_spider/middleware.py
test/baidu_spider/pipeline.py
test/baidu_spider/run.py
test/baidu_spider/settings.py
test/baidu_spider/spiders/__init__.py
test/baidu_spider/spiders/baidu.py
test/baidu_spider/spiders/nation.py
test/baidu_spider/spiders/weibo.py
test/misc/__init__.py
test/misc/demo1.py
test/misc/demo2.py
test/misc/demo3.py
test/misc/demo4.py
test/misc/demo5.py
test/misc/demo6.py
spiderswarm-0.1.0.dist-info/METADATA
spiderswarm-0.1.0.dist-info/WHEEL
spiderswarm-0.1.0.dist-info/top_level.txt
spiderswarm-0.1.0.dist-info/RECORD
